pallo/__init__.py
pallo/pallo.py
pallo-0.2.1.dist-info/LICENSE.txt
pallo-0.2.1.dist-info/METADATA
pallo-0.2.1.dist-info/WHEEL
pallo-0.2.1.dist-info/top_level.txt
pallo-0.2.1.dist-info/RECORD
