Metadata-Version: 2.1
Name: pallo
Version: 0.2.1
Summary: Simplifies the creation and usage of probabilistic asset allocation models
Home-page: https://github.com/jf225/pallo
Author: James Fahey
Author-email: <jamesaf36@gmail.com>
License: MIT
Keywords: python,finance,stocks,asset allocation,probabilities
Platform: UNKNOWN
Classifier: Development Status :: 3 - Alpha
Classifier: Intended Audience :: Financial and Insurance Industry
Classifier: Intended Audience :: Developers
Classifier: Intended Audience :: Science/Research
Classifier: Programming Language :: Python :: 3
Classifier: License :: OSI Approved :: MIT License
Classifier: Operating System :: Unix
Classifier: Operating System :: MacOS :: MacOS X
Classifier: Operating System :: Microsoft :: Windows
License-File: LICENSE.txt
Requires-Dist: tqdm (>=4.64.0)
Requires-Dist: numpy (>=1.26.1)
Requires-Dist: scipy (>=1.7.3)
Requires-Dist: yfinance (>=0.2.14)
Requires-Dist: pandas-datareader (>=0.10.0)
